phyltr/__init__.py
phyltr/__main__.py
phyltr/commands/__init__.py
phyltr/commands/annotate.py
phyltr/commands/assert.py
phyltr/commands/base.py
phyltr/commands/cat.py
phyltr/commands/clades.py
phyltr/commands/collapse.py
phyltr/commands/consensus.py
phyltr/commands/dedupe.py
phyltr/commands/grep.py
phyltr/commands/height.py
phyltr/commands/length.py
phyltr/commands/plot.py
phyltr/commands/pretty.py
phyltr/commands/prune.py
phyltr/commands/rename.py
phyltr/commands/scale.py
phyltr/commands/sibling.py
phyltr/commands/stat.py
phyltr/commands/subtree.py
phyltr/commands/support.py
phyltr/commands/taxa.py
phyltr/commands/uniq.py
phyltr/plumbing/__init__.py
phyltr/plumbing/sinks.py
phyltr/plumbing/sources.py
phyltr/utils/__init__.py
phyltr/utils/cladeprob.py
phyltr/utils/misc.py
phyltr/utils/phyltroptparse.py
phyltr/utils/topouniq.py
phyltr-0.5.0.dist-info/LICENSE
phyltr-0.5.0.dist-info/METADATA
phyltr-0.5.0.dist-info/WHEEL
phyltr-0.5.0.dist-info/entry_points.txt
phyltr-0.5.0.dist-info/top_level.txt
phyltr-0.5.0.dist-info/RECORD
